pyshikiapi/__init__.py
pyshikiapi/api.py
pyshikiapi/request.py
pyshikiapi-1.0.2.dist-info/LICENSE
pyshikiapi-1.0.2.dist-info/METADATA
pyshikiapi-1.0.2.dist-info/WHEEL
pyshikiapi-1.0.2.dist-info/top_level.txt
pyshikiapi-1.0.2.dist-info/RECORD
