Metadata-Version: 2.1
Name: pyshikiapi
Version: 1.0.2
Summary: Python wrapper for shikimori API
Home-page: https://github.com/a68366/pyshikiapi
Author: a68366
License: UNKNOWN
Platform: UNKNOWN
Classifier: Programming Language :: Python :: 3
Classifier: Intended Audience :: Developers
Classifier: License :: OSI Approved :: Apache Software License
Classifier: Operating System :: OS Independent
License-File: LICENSE
Requires-Dist: requests-oauthlib
